howto/__init__.py
howto/_version.py
howto/examples.py
howto/main.py
howto_ai-0.1.2.dist-info/METADATA
howto_ai-0.1.2.dist-info/WHEEL
howto_ai-0.1.2.dist-info/entry_points.txt
howto_ai-0.1.2.dist-info/top_level.txt
howto_ai-0.1.2.dist-info/RECORD
