Metadata-Version: 2.2
Name: howto-ai
Version: 0.1.2
Summary: Add your description here
Requires-Python: >=3.12
Requires-Dist: litellm>=1.52.12
Requires-Dist: pydantic-settings>=2.6.1
Requires-Dist: tomli-w>=1.1.0
Requires-Dist: typer>=0.13.1
Provides-Extra: dev
Requires-Dist: build>=1.2.2.post1; extra == "dev"
Requires-Dist: pre-commit>=4.0.1; extra == "dev"
Requires-Dist: pytest>=8.3.3; extra == "dev"
Requires-Dist: ruff>=0.7.4; extra == "dev"
Requires-Dist: setuptools-scm>=8.1.0; extra == "dev"
